{"chunk_definitions":[{"row":41,"row_count":1,"visible":true,"expansion_state":0,"options":{"engine":"r","include":false,"label":"unnamed-chunk-1"},"document_id":"94AB711D","chunk_id":"cgztys85h9o3w","chunk_label":"unnamed-chunk-1"},{"row":78,"row_count":1,"visible":true,"expansion_state":0,"options":{"engine":"r","results":"D_h","echo":false,"label":"example-SAMprior-SAM_weight-2"},"document_id":"88470886","chunk_id":"cki0xyakqz5ne","chunk_label":"unnamed-chunk-2"},{"row":104,"row_count":1,"visible":true,"expansion_state":0,"options":{"engine":"r","label":"example-SAMprior-SAM_weight-3"},"document_id":"88470886","chunk_id":"cd80vaxbgy8sy","chunk_label":"unnamed-chunk-3"},{"row":164,"row_count":1,"visible":true,"expansion_state":0,"options":{"engine":"r","label":"example-SAMprior-SAM_weight-4"},"document_id":"88470886","chunk_id":"clxwvex2a7f5x","chunk_label":"unnamed-chunk-4"},{"row":177,"row_count":1,"visible":true,"expansion_state":0,"options":{"engine":"r","label":"example-SAMprior-SAM_weight-5"},"document_id":"88470886","chunk_id":"co94tauii7pvu","chunk_label":"unnamed-chunk-5"},{"row":207,"row_count":1,"visible":true,"expansion_state":0,"options":{"engine":"r","echo":false,"message":false,"label":"unnamed-chunk-13"},"document_id":"88470886","chunk_id":"clnauu76y9w7o","chunk_label":"unnamed-chunk-6"},{"row":222,"row_count":1,"visible":true,"expansion_state":0,"options":{"engine":"r","label":"example-SAMprior-SAM_weight-8"},"document_id":"88470886","chunk_id":"c2p2j23u2e22x","chunk_label":"unnamed-chunk-7"},{"row":289,"row_count":1,"visible":true,"expansion_state":0,"options":{"engine":"r","label":"example-SAMprior-SAM_weight-9"},"document_id":"88470886","chunk_id":"cm1yl1039m0n4","chunk_label":"unnamed-chunk-8"},{"row":313,"row_count":1,"visible":true,"expansion_state":0,"options":{"engine":"r","label":"example-SAMprior-SAM_weight-12"},"document_id":"88470886","chunk_id":"ckguvxsm180vc","chunk_label":"unnamed-chunk-9"},{"row":337,"row_count":1,"visible":true,"expansion_state":0,"options":{"engine":"r","message":false,"label":"example-SAMprior-SAM_weight-13"},"document_id":"88470886","chunk_id":"ciit0ele8l7n1","chunk_label":"unnamed-chunk-10"}],"doc_write_time":1690946946,"chunk_rendered_width":700}